{
  "run_id": "run_bad_fnv_hash",
  "applet_id": "applet_replay_minimal",
  "code_hash": "fnv1a64:0123456789abcdef",
  "input": {
    "name": "Ada"
  },
  "random_seed": 42,
  "time_start": 1700000000000,
  "calls": [
    {
      "seq": 0,
      "method": "time.now",
      "args": null,
      "response": 1700000000000
    },
    {
      "seq": 1,
      "method": "storage.set",
      "args": [
        "lastGreeting",
        {
          "name": "Ada",
          "at": 1700000000000
        }
      ],
      "response": null
    }
  ],
  "logs": [
    "stored greeting for Ada"
  ],
  "outcome": {
    "status": "completed",
    "result": {
      "ok": true,
      "value": {
        "greeting": "Hello Ada",
        "at": 1700000000000
      }
    }
  }
}
